task_automation/__init__.py
task_automation-0.0.1.dist-info/LICENCE
task_automation-0.0.1.dist-info/METADATA
task_automation-0.0.1.dist-info/WHEEL
task_automation-0.0.1.dist-info/top_level.txt
task_automation-0.0.1.dist-info/RECORD
