Metadata-Version: 2.1
Name: task-automation
Version: 0.0.1
Summary: Package contains functions to perform simple task such as FTP transfer, Import to miscrosoft database etc.
Home-page: UNKNOWN
Author: Yogesh Khuha
Author-email: yogesh.khuha@gmail.com
License: MIT
Platform: UNKNOWN
License-File: LICENCE
